smsprofi_client/client.py
smsprofi_client-0.1.0.dist-info/WHEEL
smsprofi_client-0.1.0.dist-info/METADATA
smsprofi_client-0.1.0.dist-info/RECORD
