Metadata-Version: 2.1
Name: smsprofi-client
Version: 0.1.0
Summary: 
Author: roci
Author-email: you@example.com
Requires-Python: >=3.8,<4.0
Classifier: Programming Language :: Python :: 3
Classifier: Programming Language :: Python :: 3.8
Classifier: Programming Language :: Python :: 3.9
Requires-Dist: python-decouple (>=3.4,<4.0)
Requires-Dist: requests (>=2.25.1,<3.0.0)
